chess_graph/__init__.py
chess_graph/chart.py
chess_graph/chess_scrape.py
chess_graph/find_opening.py
chess_graph/game_parser.py
chess_graph/new_parser.py
chess_graph/elo_reading/openings_sheet.csv
chessgr/__init__.py
chessgr/chart.py
chessgr/chess_scrape.py
chessgr/find_opening.py
chessgr/game_parser.py
chess_graph-1.7.5.dist-info/LICENSE
chess_graph-1.7.5.dist-info/METADATA
chess_graph-1.7.5.dist-info/WHEEL
chess_graph-1.7.5.dist-info/top_level.txt
chess_graph-1.7.5.dist-info/RECORD
