Metadata-Version: 2.1
Name: chess-graph
Version: 1.7.5
Summary: A package that can create an interactive multi-level, shaded, piechart visualization of chess games.
Home-page: https://github.com/Destaq/chess_graph
Author: Simon Ilincev
Author-email: trilogicworlds@gmail.com
License: 'MIT'
Platform: UNKNOWN
Classifier: Programming Language :: Python :: 3
Classifier: License :: OSI Approved :: MIT License
Classifier: Operating System :: OS Independent
Requires-Python: >=3.6
